LICENSE
README.rst
setup.py
webmake/__init__.py
webmake/__main__.py
webmake/api.py
webmake/compiler.py
webmake/main.py
webmake/package.json
webmake/settings.py
webmake/watcher.py
webmake.egg-info/PKG-INFO
webmake.egg-info/SOURCES.txt
webmake.egg-info/dependency_links.txt
webmake.egg-info/entry_points.txt
webmake.egg-info/requires.txt
webmake.egg-info/top_level.txt
webmake/cordova/hooks/before_prepare/runwebmake.py
webmake/django/__init__.py
webmake/django/middleware.py
webmake/modules/__init__.py
webmake/modules/browserify.py
webmake/modules/concat.py
webmake/modules/copyfiles.py
webmake/modules/less.py
webmake/modules/minify.py
webmake/modules/sass.py
webmake/modules/utils.py