Metadata-Version: 2.1
Name: webmake
Version: 4.0.0
Summary: A simple pythonic build system for Web and Cordova projects (JS, Less, Sass...)
Home-page: https://github.com/bazzisoft/webmake
Author: Barak Shohat
Author-email: barak@bazzisoft.com
License: MIT
Keywords: make makefile build tool packaging web javascript less sass
Platform: UNKNOWN
Classifier: Development Status :: 5 - Production/Stable
Classifier: Intended Audience :: Developers
Classifier: Topic :: Software Development :: Build Tools
Classifier: License :: OSI Approved :: MIT License
Classifier: Programming Language :: Python :: 3
Classifier: Programming Language :: Python :: 3.4
Classifier: Programming Language :: Python :: 3.5
Classifier: Programming Language :: Python :: 3.6
Classifier: Programming Language :: Python :: 3.7
Classifier: Programming Language :: Python :: 3.8
Classifier: Programming Language :: Python :: 3.9
Classifier: Programming Language :: Python :: 3.10
